path_analysis_toolbox/TestClass.py
path_analysis_toolbox/__init__.py
path_analysis_toolbox/path_analysis_toolbox.py
path_analysis_toolbox-0.0.3.dist-info/METADATA
path_analysis_toolbox-0.0.3.dist-info/WHEEL
path_analysis_toolbox-0.0.3.dist-info/top_level.txt
path_analysis_toolbox-0.0.3.dist-info/RECORD
